shared_call_py/__init__.py
shared_call_py/_async.py
shared_call_py/_core.py
shared_call_py/_sync.py
shared_call_py-0.1.2.dist-info/METADATA
shared_call_py-0.1.2.dist-info/WHEEL
shared_call_py-0.1.2.dist-info/licenses/LICENSE
shared_call_py-0.1.2.dist-info/RECORD
