Metadata-Version: 2.4
Name: shared-call-py
Version: 0.1.2
Summary: Request coalescing for Python - eliminate redundant work and protect your systems from thundering herds
License-File: LICENSE
Author: SohamRatnaparkhi
Author-email: soham.ratnaparkhi@gmail.com
Requires-Python: >=3.12
Classifier: Programming Language :: Python :: 3
Classifier: Programming Language :: Python :: 3.12
Classifier: Programming Language :: Python :: 3.13
Classifier: Programming Language :: Python :: 3.14
Project-URL: Homepage, https://github.com/SohamRatnaparkhi/shared-call-py
Project-URL: Repository, https://github.com/SohamRatnaparkhi/shared-call-py
